nonebot_plugin_maze/Maze.py
nonebot_plugin_maze/__init__.py
nonebot_plugin_maze/__main__.py
nonebot_plugin_maze/config.py
nonebot_plugin_maze/metadata.py
nonebot_plugin_maze/utils.py
nonebot_plugin_maze-0.2.4.dist-info/LICENSE
nonebot_plugin_maze-0.2.4.dist-info/METADATA
nonebot_plugin_maze-0.2.4.dist-info/WHEEL
nonebot_plugin_maze-0.2.4.dist-info/top_level.txt
nonebot_plugin_maze-0.2.4.dist-info/RECORD
