Metadata-Version: 2.1
Name: nonebot-plugin-maze
Version: 0.2.4
Summary: NoneBot2交互式走迷宫插件
Home-page: https://github.com/EtherLeaF/nonebot_plugin_maze
Author: EtherLeaF
Author-email: thetapilla@gmail.com
Keywords: pip,nonebot2,nonebot,nonebot_plugin
Platform: any
Classifier: Programming Language :: Python :: 3
Classifier: License :: OSI Approved :: MIT License
Classifier: Operating System :: OS Independent
Requires-Python: >=3.8
License-File: LICENSE
Requires-Dist: nonebot-adapter-onebot (>=2.1.0)
Requires-Dist: nonebot2 (>=2.0.0-beta.2)
Requires-Dist: numpy (>=1.24.0)
Requires-Dist: pillow (>=9.0.0)
Requires-Dist: asyncer (>=0.0.1)
